{
  "data": [
    {
      "index": 0,
      "age_1a_q_1": 552,
      "gender_T1_M": "FEMALE",
      "bodylength_cm_all_m_1_T1_M": 181,
      "bodyweight_kg_all_m_1_T1_M": 113
    },
    {
      "index": 1,
      "age_1a_q_1": 381,
      "gender_T1_M": "FEMALE",
      "bodylength_cm_all_m_1_T1_M": 161,
      "bodyweight_kg_all_m_1_T1_M": 77
    },
    {
      "index": 2,
      "age_1a_q_1": 456,
      "gender_T1_M": "FEMALE",
      "bodylength_cm_all_m_1_T1_M": 185,
      "bodyweight_kg_all_m_1_T1_M": 75
    },
    {
      "index": 3,
      "age_1a_q_1": 289,
      "gender_T1_M": "FEMALE",
      "bodylength_cm_all_m_1_T1_M": 186,
      "bodyweight_kg_all_m_1_T1_M": 77
    },
    {
      "index": 4,
      "age_1a_q_1": 604,
      "gender_T1_M": "MALE",
      "bodylength_cm_all_m_1_T1_M": 196,
      "bodyweight_kg_all_m_1_T1_M": 97
    },
    {
      "index": 5,
      "age_1a_q_1": 356,
      "gender_T1_M": "FEMALE",
      "bodylength_cm_all_m_1_T1_M": 182.5,
      "bodyweight_kg_all_m_1_T1_M": 63
    },
    {
      "index": 6,
      "age_1a_q_1": 379,
      "gender_T1_M": "FEMALE",
      "bodylength_cm_all_m_1_T1_M": 160,
      "bodyweight_kg_all_m_1_T1_M": 51.5
    },
    {
      "index": 7,
      "age_1a_q_1": 891,
      "gender_T1_M": "FEMALE",
      "bodylength_cm_all_m_1_T1_M": 161,
      "bodyweight_kg_all_m_1_T1_M": 110
    },
    {
      "index": 8,
      "age_1a_q_1": 647,
      "gender_T1_M": "MALE",
      "bodylength_cm_all_m_1_T1_M": 181,
      "bodyweight_kg_all_m_1_T1_M": 91
    },
    {
      "index": 9,
      "age_1a_q_1": 716,
      "gender_T1_M": "FEMALE",
      "bodylength_cm_all_m_1_T1_M": 170,
      "bodyweight_kg_all_m_1_T1_M": 68.5
    },
    {
      "index": 10,
      "age_1a_q_1": 663,
      "gender_T1_M": "FEMALE",
      "bodylength_cm_all_m_1_T1_M": 174,
      "bodyweight_kg_all_m_1_T1_M": 91
    },
    {
      "index": 11,
      "age_1a_q_1": 705,
      "gender_T1_M": "MALE",
      "bodylength_cm_all_m_1_T1_M": 187,
      "bodyweight_kg_all_m_1_T1_M": 98
    },
    {
      "index": 12,
      "age_1a_q_1": 463,
      "gender_T1_M": "MALE",
      "bodylength_cm_all_m_1_T1_M": 183,
      "bodyweight_kg_all_m_1_T1_M": 67
    },
    {
      "index": 13,
      "age_1a_q_1": 591,
      "gender_T1_M": "MALE",
      "bodylength_cm_all_m_1_T1_M": 184.5,
      "bodyweight_kg_all_m_1_T1_M": 86.5
    },
    {
      "index": 14,
      "age_1a_q_1": 475,
      "gender_T1_M": "FEMALE",
      "bodylength_cm_all_m_1_T1_M": 170,
      "bodyweight_kg_all_m_1_T1_M": 92
    },
    {
      "index": 15,
      "age_1a_q_1": 570,
      "gender_T1_M": "MALE",
      "bodylength_cm_all_m_1_T1_M": 174.7,
      "bodyweight_kg_all_m_1_T1_M": 101.5
    },
    {
      "index": 16,
      "age_1a_q_1": 400,
      "gender_T1_M": "FEMALE",
      "bodylength_cm_all_m_1_T1_M": 175,
      "bodyweight_kg_all_m_1_T1_M": 63
    },
    {
      "index": 17,
      "age_1a_q_1": 365,
      "gender_T1_M": "MALE",
      "bodylength_cm_all_m_1_T1_M": 190,
      "bodyweight_kg_all_m_1_T1_M": 73
    },
    {
      "index": 18,
      "age_1a_q_1": 469,
      "gender_T1_M": "MALE",
      "bodylength_cm_all_m_1_T1_M": 185.5,
      "bodyweight_kg_all_m_1_T1_M": 98
    },
    {
      "index": 19,
      "age_1a_q_1": 534,
      "gender_T1_M": "FEMALE",
      "bodylength_cm_all_m_1_T1_M": 173,
      "bodyweight_kg_all_m_1_T1_M": 64
    },
    {
      "index": 20,
      "age_1a_q_1": 550,
      "gender_T1_M": "MALE",
      "bodylength_cm_all_m_1_T1_M": 192,
      "bodyweight_kg_all_m_1_T1_M": 119
    },
    {
      "index": 21,
      "age_1a_q_1": 713,
      "gender_T1_M": "MALE",
      "bodylength_cm_all_m_1_T1_M": 175.5,
      "bodyweight_kg_all_m_1_T1_M": 82
    },
    {
      "index": 22,
      "age_1a_q_1": 510,
      "gender_T1_M": "FEMALE",
      "bodylength_cm_all_m_1_T1_M": 173,
      "bodyweight_kg_all_m_1_T1_M": 77
    },
    {
      "index": 23,
      "age_1a_q_1": 480,
      "gender_T1_M": "FEMALE",
      "bodylength_cm_all_m_1_T1_M": 171.5,
      "bodyweight_kg_all_m_1_T1_M": 60
    },
    {
      "index": 24,
      "age_1a_q_1": 381,
      "gender_T1_M": "MALE",
      "bodylength_cm_all_m_1_T1_M": 179,
      "bodyweight_kg_all_m_1_T1_M": 72
    },
    {
      "index": 25,
      "age_1a_q_1": 585,
      "gender_T1_M": "FEMALE",
      "bodylength_cm_all_m_1_T1_M": 178,
      "bodyweight_kg_all_m_1_T1_M": 68
    },
    {
      "index": 26,
      "age_1a_q_1": 531,
      "gender_T1_M": "FEMALE",
      "bodylength_cm_all_m_1_T1_M": 180,
      "bodyweight_kg_all_m_1_T1_M": 78
    },
    {
      "index": 27,
      "age_1a_q_1": 435,
      "gender_T1_M": "FEMALE",
      "bodylength_cm_all_m_1_T1_M": 167.5,
      "bodyweight_kg_all_m_1_T1_M": 61
    },
    {
      "index": 28,
      "age_1a_q_1": 505,
      "gender_T1_M": "FEMALE",
      "bodylength_cm_all_m_1_T1_M": 167,
      "bodyweight_kg_all_m_1_T1_M": 56
    },
    {
      "index": 29,
      "age_1a_q_1": 728,
      "gender_T1_M": "MALE",
      "bodylength_cm_all_m_1_T1_M": 173,
      "bodyweight_kg_all_m_1_T1_M": 79
    },
    {
      "index": 30,
      "age_1a_q_1": 592,
      "gender_T1_M": "FEMALE",
      "bodylength_cm_all_m_1_T1_M": 159.5,
      "bodyweight_kg_all_m_1_T1_M": 68
    },
    {
      "index": 31,
      "age_1a_q_1": 565,
      "gender_T1_M": "FEMALE",
      "bodylength_cm_all_m_1_T1_M": 172,
      "bodyweight_kg_all_m_1_T1_M": 93
    },
    {
      "index": 32,
      "age_1a_q_1": 577,
      "gender_T1_M": "FEMALE",
      "bodylength_cm_all_m_1_T1_M": 164,
      "bodyweight_kg_all_m_1_T1_M": 54
    },
    {
      "index": 33,
      "age_1a_q_1": 541,
      "gender_T1_M": "FEMALE",
      "bodylength_cm_all_m_1_T1_M": 159,
      "bodyweight_kg_all_m_1_T1_M": 71
    },
    {
      "index": 34,
      "age_1a_q_1": 351,
      "gender_T1_M": "FEMALE",
      "bodylength_cm_all_m_1_T1_M": 174.5,
      "bodyweight_kg_all_m_1_T1_M": 73
    },
    {
      "index": 35,
      "age_1a_q_1": 680,
      "gender_T1_M": "FEMALE",
      "bodylength_cm_all_m_1_T1_M": 176,
      "bodyweight_kg_all_m_1_T1_M": 98
    },
    {
      "index": 36,
      "age_1a_q_1": 450,
      "gender_T1_M": "MALE",
      "bodylength_cm_all_m_1_T1_M": 179,
      "bodyweight_kg_all_m_1_T1_M": 89
    },
    {
      "index": 37,
      "age_1a_q_1": 550,
      "gender_T1_M": "FEMALE",
      "bodylength_cm_all_m_1_T1_M": 169.5,
      "bodyweight_kg_all_m_1_T1_M": 80
    },
    {
      "index": 38,
      "age_1a_q_1": 579,
      "gender_T1_M": "FEMALE",
      "bodylength_cm_all_m_1_T1_M": 173.5,
      "bodyweight_kg_all_m_1_T1_M": 73.5
    },
    {
      "index": 39,
      "age_1a_q_1": 494,
      "gender_T1_M": "MALE",
      "bodylength_cm_all_m_1_T1_M": 180,
      "bodyweight_kg_all_m_1_T1_M": 82
    },
    {
      "index": 40,
      "age_1a_q_1": 404,
      "gender_T1_M": "MALE",
      "bodylength_cm_all_m_1_T1_M": 184,
      "bodyweight_kg_all_m_1_T1_M": 78
    },
    {
      "index": 41,
      "age_1a_q_1": 571,
      "gender_T1_M": "FEMALE",
      "bodylength_cm_all_m_1_T1_M": 178.5,
      "bodyweight_kg_all_m_1_T1_M": 104
    },
    {
      "index": 42,
      "age_1a_q_1": 402,
      "gender_T1_M": "MALE",
      "bodylength_cm_all_m_1_T1_M": 182,
      "bodyweight_kg_all_m_1_T1_M": 116
    },
    {
      "index": 43,
      "age_1a_q_1": 236,
      "gender_T1_M": "FEMALE",
      "bodylength_cm_all_m_1_T1_M": 170.5,
      "bodyweight_kg_all_m_1_T1_M": 80
    },
    {
      "index": 44,
      "age_1a_q_1": 385,
      "gender_T1_M": "MALE",
      "bodylength_cm_all_m_1_T1_M": 180,
      "bodyweight_kg_all_m_1_T1_M": 94
    },
    {
      "index": 45,
      "age_1a_q_1": 693,
      "gender_T1_M": "MALE",
      "bodylength_cm_all_m_1_T1_M": 172.5,
      "bodyweight_kg_all_m_1_T1_M": 80
    },
    {
      "index": 46,
      "age_1a_q_1": 553,
      "gender_T1_M": "FEMALE",
      "bodylength_cm_all_m_1_T1_M": 168,
      "bodyweight_kg_all_m_1_T1_M": 72
    },
    {
      "index": 47,
      "age_1a_q_1": 618,
      "gender_T1_M": "MALE",
      "bodylength_cm_all_m_1_T1_M": 178,
      "bodyweight_kg_all_m_1_T1_M": 88
    },
    {
      "index": 48,
      "age_1a_q_1": 431,
      "gender_T1_M": "MALE",
      "bodylength_cm_all_m_1_T1_M": 196.5,
      "bodyweight_kg_all_m_1_T1_M": 78
    },
    {
      "index": 49,
      "age_1a_q_1": 531,
      "gender_T1_M": "FEMALE",
      "bodylength_cm_all_m_1_T1_M": 169,
      "bodyweight_kg_all_m_1_T1_M": 66
    },
    {
      "index": 50,
      "age_1a_q_1": 463,
      "gender_T1_M": "MALE",
      "bodylength_cm_all_m_1_T1_M": 175.5,
      "bodyweight_kg_all_m_1_T1_M": 78
    },
    {
      "index": 51,
      "age_1a_q_1": 567,
      "gender_T1_M": "MALE",
      "bodylength_cm_all_m_1_T1_M": 177.5,
      "bodyweight_kg_all_m_1_T1_M": 96
    },
    {
      "index": 52,
      "age_1a_q_1": 593,
      "gender_T1_M": "FEMALE",
      "bodylength_cm_all_m_1_T1_M": 153,
      "bodyweight_kg_all_m_1_T1_M": 79
    },
    {
      "index": 53,
      "age_1a_q_1": 523,
      "gender_T1_M": "MALE",
      "bodylength_cm_all_m_1_T1_M": 183,
      "bodyweight_kg_all_m_1_T1_M": 84
    },
    {
      "index": 54,
      "age_1a_q_1": 675,
      "gender_T1_M": "FEMALE",
      "bodylength_cm_all_m_1_T1_M": 168,
      "bodyweight_kg_all_m_1_T1_M": 57.5
    },
    {
      "index": 55,
      "age_1a_q_1": 568,
      "gender_T1_M": "MALE",
      "bodylength_cm_all_m_1_T1_M": 184,
      "bodyweight_kg_all_m_1_T1_M": 81
    },
    {
      "index": 56,
      "age_1a_q_1": 759,
      "gender_T1_M": "FEMALE",
      "bodylength_cm_all_m_1_T1_M": 166,
      "bodyweight_kg_all_m_1_T1_M": 53.5
    },
    {
      "index": 57,
      "age_1a_q_1": 470,
      "gender_T1_M": "MALE",
      "bodylength_cm_all_m_1_T1_M": 172.5,
      "bodyweight_kg_all_m_1_T1_M": 81
    },
    {
      "index": 58,
      "age_1a_q_1": 743,
      "gender_T1_M": "FEMALE",
      "bodylength_cm_all_m_1_T1_M": 167,
      "bodyweight_kg_all_m_1_T1_M": 77
    },
    {
      "index": 59,
      "age_1a_q_1": 427,
      "gender_T1_M": "MALE",
      "bodylength_cm_all_m_1_T1_M": 187,
      "bodyweight_kg_all_m_1_T1_M": 85
    },
    {
      "index": 60,
      "age_1a_q_1": 469,
      "gender_T1_M": "FEMALE",
      "bodylength_cm_all_m_1_T1_M": 172.5,
      "bodyweight_kg_all_m_1_T1_M": 82.5
    },
    {
      "index": 61,
      "age_1a_q_1": 304,
      "gender_T1_M": "FEMALE",
      "bodylength_cm_all_m_1_T1_M": 170,
      "bodyweight_kg_all_m_1_T1_M": 61
    },
    {
      "index": 62,
      "age_1a_q_1": 541,
      "gender_T1_M": "MALE",
      "bodylength_cm_all_m_1_T1_M": 201,
      "bodyweight_kg_all_m_1_T1_M": 89
    },
    {
      "index": 63,
      "age_1a_q_1": 335,
      "gender_T1_M": "FEMALE",
      "bodylength_cm_all_m_1_T1_M": 178,
      "bodyweight_kg_all_m_1_T1_M": 71
    },
    {
      "index": 64,
      "age_1a_q_1": 576,
      "gender_T1_M": "MALE",
      "bodylength_cm_all_m_1_T1_M": 189,
      "bodyweight_kg_all_m_1_T1_M": 100
    },
    {
      "index": 65,
      "age_1a_q_1": 702,
      "gender_T1_M": "FEMALE",
      "bodylength_cm_all_m_1_T1_M": 177.5,
      "bodyweight_kg_all_m_1_T1_M": 85
    },
    {
      "index": 66,
      "age_1a_q_1": 472,
      "gender_T1_M": "MALE",
      "bodylength_cm_all_m_1_T1_M": 187.5,
      "bodyweight_kg_all_m_1_T1_M": 101
    },
    {
      "index": 67,
      "age_1a_q_1": 458,
      "gender_T1_M": "FEMALE",
      "bodylength_cm_all_m_1_T1_M": 165,
      "bodyweight_kg_all_m_1_T1_M": 63.5
    },
    {
      "index": 68,
      "age_1a_q_1": 231,
      "gender_T1_M": "FEMALE",
      "bodylength_cm_all_m_1_T1_M": 156,
      "bodyweight_kg_all_m_1_T1_M": 66
    },
    {
      "index": 69,
      "age_1a_q_1": 609,
      "gender_T1_M": "FEMALE",
      "bodylength_cm_all_m_1_T1_M": 165,
      "bodyweight_kg_all_m_1_T1_M": 86
    },
    {
      "index": 70,
      "age_1a_q_1": 745,
      "gender_T1_M": "MALE",
      "bodylength_cm_all_m_1_T1_M": 170.5,
      "bodyweight_kg_all_m_1_T1_M": 80
    },
    {
      "index": 71,
      "age_1a_q_1": 604,
      "gender_T1_M": "MALE",
      "bodylength_cm_all_m_1_T1_M": 175,
      "bodyweight_kg_all_m_1_T1_M": 91
    },
    {
      "index": 72,
      "age_1a_q_1": 537,
      "gender_T1_M": "FEMALE",
      "bodylength_cm_all_m_1_T1_M": 168.5,
      "bodyweight_kg_all_m_1_T1_M": 63
    },
    {
      "index": 73,
      "age_1a_q_1": 500,
      "gender_T1_M": "FEMALE",
      "bodylength_cm_all_m_1_T1_M": 170.5,
      "bodyweight_kg_all_m_1_T1_M": 65
    },
    {
      "index": 74,
      "age_1a_q_1": 573,
      "gender_T1_M": "FEMALE",
      "bodylength_cm_all_m_1_T1_M": 172,
      "bodyweight_kg_all_m_1_T1_M": 63
    },
    {
      "index": 75,
      "age_1a_q_1": 490,
      "gender_T1_M": "FEMALE",
      "bodylength_cm_all_m_1_T1_M": 163.5,
      "bodyweight_kg_all_m_1_T1_M": 58
    },
    {
      "index": 76,
      "age_1a_q_1": 757,
      "gender_T1_M": "MALE",
      "bodylength_cm_all_m_1_T1_M": 186,
      "bodyweight_kg_all_m_1_T1_M": 98
    },
    {
      "index": 77,
      "age_1a_q_1": 431,
      "gender_T1_M": "FEMALE",
      "bodylength_cm_all_m_1_T1_M": 175.5,
      "bodyweight_kg_all_m_1_T1_M": 62
    },
    {
      "index": 78,
      "age_1a_q_1": 486,
      "gender_T1_M": "FEMALE",
      "bodylength_cm_all_m_1_T1_M": 165,
      "bodyweight_kg_all_m_1_T1_M": 69
    },
    {
      "index": 79,
      "age_1a_q_1": 763,
      "gender_T1_M": "FEMALE",
      "bodylength_cm_all_m_1_T1_M": 171,
      "bodyweight_kg_all_m_1_T1_M": 70.5
    },
    {
      "index": 80,
      "age_1a_q_1": 391,
      "gender_T1_M": "FEMALE",
      "bodylength_cm_all_m_1_T1_M": 157,
      "bodyweight_kg_all_m_1_T1_M": 46
    },
    {
      "index": 81,
      "age_1a_q_1": 300,
      "gender_T1_M": "MALE",
      "bodylength_cm_all_m_1_T1_M": 172.5,
      "bodyweight_kg_all_m_1_T1_M": 78
    },
    {
      "index": 82,
      "age_1a_q_1": 463,
      "gender_T1_M": "FEMALE",
      "bodylength_cm_all_m_1_T1_M": 176.5,
      "bodyweight_kg_all_m_1_T1_M": 108.5
    },
    {
      "index": 83,
      "age_1a_q_1": 467,
      "gender_T1_M": "FEMALE",
      "bodylength_cm_all_m_1_T1_M": 180,
      "bodyweight_kg_all_m_1_T1_M": 70.5
    },
    {
      "index": 84,
      "age_1a_q_1": 583,
      "gender_T1_M": "FEMALE",
      "bodylength_cm_all_m_1_T1_M": 160,
      "bodyweight_kg_all_m_1_T1_M": 78
    },
    {
      "index": 85,
      "age_1a_q_1": 306,
      "gender_T1_M": "MALE",
      "bodylength_cm_all_m_1_T1_M": 182,
      "bodyweight_kg_all_m_1_T1_M": 70
    },
    {
      "index": 86,
      "age_1a_q_1": 401,
      "gender_T1_M": "MALE",
      "bodylength_cm_all_m_1_T1_M": 181,
      "bodyweight_kg_all_m_1_T1_M": 68
    },
    {
      "index": 87,
      "age_1a_q_1": 471,
      "gender_T1_M": "MALE",
      "bodylength_cm_all_m_1_T1_M": 191.5,
      "bodyweight_kg_all_m_1_T1_M": 122
    },
    {
      "index": 88,
      "age_1a_q_1": 776,
      "gender_T1_M": "MALE",
      "bodylength_cm_all_m_1_T1_M": 182,
      "bodyweight_kg_all_m_1_T1_M": 88.5
    },
    {
      "index": 89,
      "age_1a_q_1": 807,
      "gender_T1_M": "MALE",
      "bodylength_cm_all_m_1_T1_M": 171,
      "bodyweight_kg_all_m_1_T1_M": 113
    },
    {
      "index": 90,
      "age_1a_q_1": 931,
      "gender_T1_M": "MALE",
      "bodylength_cm_all_m_1_T1_M": 186,
      "bodyweight_kg_all_m_1_T1_M": 85
    },
    {
      "index": 91,
      "age_1a_q_1": 784,
      "gender_T1_M": "FEMALE",
      "bodylength_cm_all_m_1_T1_M": 153,
      "bodyweight_kg_all_m_1_T1_M": 78
    },
    {
      "index": 92,
      "age_1a_q_1": 555,
      "gender_T1_M": "MALE",
      "bodylength_cm_all_m_1_T1_M": 194,
      "bodyweight_kg_all_m_1_T1_M": 107
    },
    {
      "index": 93,
      "age_1a_q_1": 581,
      "gender_T1_M": "FEMALE",
      "bodylength_cm_all_m_1_T1_M": 166,
      "bodyweight_kg_all_m_1_T1_M": 74
    },
    {
      "index": 94,
      "age_1a_q_1": 568,
      "gender_T1_M": "MALE",
      "bodylength_cm_all_m_1_T1_M": 186,
      "bodyweight_kg_all_m_1_T1_M": 90
    },
    {
      "index": 95,
      "age_1a_q_1": 502,
      "gender_T1_M": "FEMALE",
      "bodylength_cm_all_m_1_T1_M": 181,
      "bodyweight_kg_all_m_1_T1_M": 94
    },
    {
      "index": 96,
      "age_1a_q_1": 729,
      "gender_T1_M": "FEMALE",
      "bodylength_cm_all_m_1_T1_M": 166,
      "bodyweight_kg_all_m_1_T1_M": 79
    },
    {
      "index": 97,
      "age_1a_q_1": 774,
      "gender_T1_M": "MALE",
      "bodylength_cm_all_m_1_T1_M": 174,
      "bodyweight_kg_all_m_1_T1_M": 71
    },
    {
      "index": 98,
      "age_1a_q_1": 505,
      "gender_T1_M": "MALE",
      "bodylength_cm_all_m_1_T1_M": 181,
      "bodyweight_kg_all_m_1_T1_M": 69
    },
    {
      "index": 99,
      "age_1a_q_1": 508,
      "gender_T1_M": "FEMALE",
      "bodylength_cm_all_m_1_T1_M": 165.5,
      "bodyweight_kg_all_m_1_T1_M": 92.5
    },
    {
      "index": 100,
      "age_1a_q_1": 510,
      "gender_T1_M": "MALE",
      "bodylength_cm_all_m_1_T1_M": 170.5,
      "bodyweight_kg_all_m_1_T1_M": 93
    }
  ]
}